shareit/__init__.py
shareit/cli.py
shareit/pyproject.toml
shareit-0.3.0.dist-info/LICENSE
shareit-0.3.0.dist-info/METADATA
shareit-0.3.0.dist-info/WHEEL
shareit-0.3.0.dist-info/entry_points.txt
shareit-0.3.0.dist-info/RECORD
