Metadata-Version: 2.3
Name: shareit
Version: 0.3.0
Summary: A simple file sharing CLI tool.
License: MIT
Author: Fahad Ahammed
Author-email: iamfahadahmed@gmail.com
Requires-Python: >=3.11,<4.0
Classifier: License :: OSI Approved :: MIT License
Classifier: Programming Language :: Python :: 3
Classifier: Programming Language :: Python :: 3.11
Classifier: Programming Language :: Python :: 3.12
Classifier: Programming Language :: Python :: 3.13
Requires-Dist: psutil (==7.0.0)
Requires-Dist: rich (==14.0.0)
